[
  {
    "id": 0,
    "name": "Sword",
    "x": 0,
    "y": 0,
    "width": 1,
    "height": 4,
    "modifiers": [{
      "attribute": "MinDamage",
      "value": 5.0,
      "scope": "Flat"
    }, {
      "attribute": "MaxDamage",
      "value": 10.0,
      "scope": "Flat"
    }, {
      "attribute": "Trigger",
      "value": "OnAttack",
      "scope": "Set"
    }]
  },
  {
    "id": 1,
    "name": "Club",
    "x": 1,
    "y": 0,
    "width": 1,
    "height": 2,
    "modifiers": [{
      "attribute": "MinDamage",
      "value": 5.0,
      "scope": "Flat"
    }, {
      "attribute": "MaxDamage",
      "value": 10.0,
      "scope": "Flat"
    }, {
      "attribute": "BaseAttackSpeed",
      "value": 0.5,
      "scope": "Flat"
    }, {
      "attribute": "Trigger",
      "value": "OnAttack",
      "scope": "Set"
    }]
  },
  {
    "id": 2,
    "name": "Rod",
    "x": 2,
    "y": 0,
    "width": 1,
    "height": 3,
    "modifiers": [{
      "attribute": "MinDamage",
      "value": 5.0,
      "scope": "Flat"
    }, {
      "attribute": "MaxDamage",
      "value": 10.0,
      "scope": "Flat"
    }, {
      "attribute": "Trigger",
      "value": "OnCast",
      "scope": "Set"
    }]
  },
  {
    "id": 3,
    "name": "Shoulder",
    "x": 3,
    "y": 0,
    "width": 1,
    "height": 2
  },
  {
    "id": 4,
    "name": "Helmet",
    "x": 4,
    "y": 0,
    "width": 2,
    "height": 2
  },
  {
    "id": 5,
    "name": "Shield",
    "x": 6,
    "y": 0,
    "width": 2,
    "height": 2,
    "modifiers": [
      {
        "attribute": "MinDamage",
        "value": 5.0,
        "scope": "Flat"
      }, {
        "attribute": "MaxDamage",
        "value": 10.0,
        "scope": "Flat"
      }, {
        "attribute": "Trigger",
        "value": "OnAttack",
        "scope": "Set"
      }
    ]
  },
  {
    "id": 6,
    "name": "Cape",
    "x": 8,
    "y": 0,
    "width": 2,
    "height": 2
  }
]